webframe_py/__init__.py
webframe_py/app.py
webframe_py/middleware.py
webframe_py/response.py
webframe_py-0.1.1.dist-info/METADATA
webframe_py-0.1.1.dist-info/WHEEL
webframe_py-0.1.1.dist-info/top_level.txt
webframe_py-0.1.1.dist-info/RECORD
